<?xml version="1.0" encoding="UTF-8"?>
<!DOCTYPE comps PUBLIC "-//Red Hat, Inc.//DTD Comps info//EN" "comps.dtd">
<comps>

  <group>
   <id>virtualmin-lamp</id>
   <default>false</default>
   <uservisible>true</uservisible>
   <display_order>1024</display_order>
   <name>Virtualmin LAMP Stack</name>
   <description>Virtualmin with Apache, MariaDB, and PHP/Perl/Python/Ruby</description>
    <packagelist>
      <packagereq type="mandatory">bind</packagereq>
      <packagereq type="mandatory">bind-utils</packagereq>
      <packagereq type="mandatory">httpd</packagereq>
      <packagereq type="mandatory">httpd-itk</packagereq>
      <packagereq type="mandatory">iptables</packagereq>
      <packagereq type="mandatory">firewalld</packagereq>
      <packagereq type="mandatory">mod_ssl</packagereq>
      <packagereq type="mandatory">openssl</packagereq>
      <packagereq type="mandatory">perl-Crypt-SSLeay</packagereq>
      <packagereq type="mandatory">perl-DBD-MySQL</packagereq>
      <packagereq type="mandatory">perl-JSON-PP</packagereq>
      <packagereq type="mandatory">perl-JSON-XS</packagereq>
      <packagereq type="mandatory">perl-Log-Log4perl</packagereq>
      <packagereq type="mandatory">perl-LWP-Protocol-https</packagereq>
      <packagereq type="mandatory">perl-XML-Simple</packagereq>
      <packagereq type="mandatory">perl-Config-IniFiles</packagereq>
      <packagereq type="mandatory">perl-Module-Load</packagereq>
      <packagereq type="mandatory">perl-Time-HiRes</packagereq>
      <packagereq type="mandatory">perl-parent</packagereq>
      <packagereq type="mandatory">php</packagereq>
      <packagereq type="mandatory">php-gd</packagereq>
      <packagereq type="mandatory">php-imap</packagereq>
      <packagereq type="mandatory">php-mbstring</packagereq>
      <packagereq type="mandatory">php-mysql</packagereq>
      <packagereq type="mandatory">php-odbc</packagereq>
      <packagereq type="mandatory">php-pear</packagereq>
      <packagereq type="mandatory">php-pgsql</packagereq>
      <packagereq type="mandatory">php-snmp</packagereq>
      <packagereq type="mandatory">php-xml</packagereq>
      <packagereq type="mandatory">php-xmlrpc</packagereq>
      <packagereq type="mandatory">python</packagereq>
      <packagereq type="mandatory">quota</packagereq>
      <packagereq type="mandatory">ruby</packagereq>
      <packagereq type="mandatory">ruby-devel</packagereq>
      <packagereq type="mandatory">rubygems</packagereq>
      <packagereq type="mandatory">ca-certificates</packagereq>
      <packagereq type="default">clamav</packagereq>
      <packagereq type="default">clamav-scanner-systemd</packagereq>
      <packagereq type="default">clamav-server</packagereq>
      <packagereq type="default">clamav-server-systemd</packagereq>
      <packagereq type="default">cyrus-sasl</packagereq>
      <packagereq type="default">cyrus-sasl-gssapi</packagereq>
      <packagereq type="default">dkim-milter</packagereq>
      <packagereq type="default">dovecot</packagereq>
      <packagereq type="default">jailkit</packagereq>
      <packagereq type="default">logrotate</packagereq>
      <packagereq type="default">mariadb</packagereq>
      <packagereq type="default">mariadb-devel</packagereq>
      <packagereq type="default">mariadb-server</packagereq>
      <packagereq type="optional">postgresql</packagereq>
      <packagereq type="optional">postgresql-devel</packagereq>
      <packagereq type="optional">postgresql-server</packagereq>
      <packagereq type="optional">perl-DBD-Pg</packagereq>
      <packagereq type="default">postgrey</packagereq>
      <packagereq type="default">procmail-wrapper</packagereq>
      <packagereq type="default">proftpd</packagereq>
      <packagereq type="default">spamassassin</packagereq>
      <packagereq type="default">webalizer</packagereq>
      <packagereq type="default">fail2ban-server</packagereq>
      <packagereq type="default">fail2ban-firewalld</packagereq>
      <packagereq type="default">awstats</packagereq>
    </packagelist>
  </group>

  <group>
   <id>virtualmin-lemp</id>
   <default>false</default>
   <uservisible>true</uservisible>
   <display_order>1024</display_order>
   <name>Virtualmin LEMP Stack</name>
   <description>Virtualmin with nginx, MariaDB, and PHP/Perl/Python/Ruby</description>
    <packagelist>
      <packagereq type="mandatory">bind</packagereq>
      <packagereq type="mandatory">bind-utils</packagereq>
      <packagereq type="mandatory">nginx</packagereq>
      <packagereq type="mandatory">iptables</packagereq>
      <packagereq type="mandatory">openssl</packagereq>
      <packagereq type="mandatory">perl-Crypt-SSLeay</packagereq>
      <packagereq type="mandatory">perl-DBD-MySQL</packagereq>
      <packagereq type="mandatory">perl-JSON-XS</packagereq>
      <packagereq type="mandatory">perl-JSON-PP</packagereq>
      <packagereq type="mandatory">perl-Log-Log4perl</packagereq>
      <packagereq type="mandatory">perl-LWP-Protocol-https</packagereq>
      <packagereq type="mandatory">perl-XML-Simple</packagereq>
      <packagereq type="mandatory">perl-Config-IniFiles</packagereq>
      <packagereq type="mandatory">perl-Module-Load</packagereq>
      <packagereq type="mandatory">perl-Time-HiRes</packagereq>
      <packagereq type="mandatory">perl-parent</packagereq>
      <packagereq type="mandatory">php</packagereq>
      <packagereq type="mandatory">php-fpm</packagereq>
      <packagereq type="mandatory">php-gd</packagereq>
      <packagereq type="mandatory">php-imap</packagereq>
      <packagereq type="mandatory">php-mbstring</packagereq>
      <packagereq type="mandatory">php-mysql</packagereq>
      <packagereq type="mandatory">php-odbc</packagereq>
      <packagereq type="mandatory">php-opcache</packagereq>
      <packagereq type="mandatory">php-pear</packagereq>
      <packagereq type="mandatory">php-pgsql</packagereq>
      <packagereq type="mandatory">php-snmp</packagereq>
      <packagereq type="mandatory">php-xml</packagereq>
      <packagereq type="mandatory">php-xmlrpc</packagereq>
      <packagereq type="mandatory">python</packagereq>
      <packagereq type="mandatory">quota</packagereq>
      <packagereq type="mandatory">ruby</packagereq>
      <packagereq type="mandatory">ruby-devel</packagereq>
      <packagereq type="mandatory">rubygems</packagereq>
      <packagereq type="default">ca-certificates</packagereq>
      <packagereq type="default">clamav</packagereq>
      <packagereq type="default">clamav-scanner-systemd</packagereq>
      <packagereq type="default">clamav-server</packagereq>
      <packagereq type="default">clamav-server-systemd</packagereq>
      <packagereq type="default">cyrus-sasl</packagereq>
      <packagereq type="default">cyrus-sasl-gssapi</packagereq>
      <packagereq type="default">dkim-milter</packagereq>
      <packagereq type="default">dovecot</packagereq>
      <packagereq type="default">jailkit</packagereq>
      <packagereq type="default">logrotate</packagereq>
      <packagereq type="default">mariadb</packagereq>
      <packagereq type="default">mariadb-devel</packagereq>
      <packagereq type="default">mariadb-server</packagereq>
      <packagereq type="optional">postgresql</packagereq>
      <packagereq type="optional">postgresql-devel</packagereq>
      <packagereq type="optional">postgresql-server</packagereq>
      <packagereq type="optional">perl-DBD-Pg</packagereq>
      <packagereq type="default">postgrey</packagereq>
      <packagereq type="default">procmail-wrapper</packagereq>
      <packagereq type="default">proftpd</packagereq>
      <packagereq type="default">spamassassin</packagereq>
      <packagereq type="default">webalizer</packagereq>
      <packagereq type="default">fail2ban-server</packagereq>
      <packagereq type="default">fail2ban-firewalld</packagereq>
      <packagereq type="default">awstats</packagereq>
    </packagelist>
  </group>

  <group>
   <id>scl-php70</id>
   <default>false</default>
   <uservisible>true</uservisible>
   <display_order>1024</display_order>
   <name>Software Collections PHP 7 Environment</name>
   <description>Most commonly used PHP 7 packages from Software Collections</description>
    <packagelist>
      <packagereq type="mandatory">rh-php70</packagereq>
      <packagereq type="mandatory">rh-php70-php</packagereq>
      <packagereq type="mandatory">rh-php70-php-fpm</packagereq>
      <packagereq type="default">rh-php70-php-bcmath</packagereq>
      <packagereq type="default">rh-php70-php-mbstring</packagereq>
      <packagereq type="default">rh-php70-php-xmlrpc</packagereq>
      <packagereq type="default">rh-php70-php-opcache</packagereq>
      <packagereq type="default">rh-php70-php-devel</packagereq>
      <packagereq type="default">rh-php70-php-gd</packagereq>
      <packagereq type="default">rh-php70-php-gdm</packagereq>
      <packagereq type="default">rh-php70-php-mysqlnd</packagereq>
      <packagereq type="default">rh-php70-php-pdo</packagereq>
      <packagereq type="default">rh-php70-php-pspell</packagereq>
    </packagelist>
  </group>
</comps>
